[{"x": -13629510.781396192, "y": 4520903.38759143, "url": "https://t.co/k8hheGbyYb", "text": "An aging Kong (aka popcorn) @EmpireStateBldg, clearly in need of a helping hand to reach the top. #NewYorkCity #NOFILTER https://t.co/R3k8GkX3Gy", "display_img": "http://pbs.twimg.com/media/DHugX5kV0AEKVDc.jpg", "media": ["http://pbs.twimg.com/media/DHugX5kV0AEKVDc.jpg"], "coords": [[[-122.514926, 37.708075], [-122.514926, 37.833238], [-122.357031, 37.833238], [-122.357031, 37.708075]]], "hashtags": ["NewYorkCity", "NOFILTER"], "time": "20170821 043039"}]